MANIFEST.in
README.md
setup.py
angler/__init__.py
angler/adjoint.py
angler/constants.py
angler/derivatives.py
angler/filter.py
angler/gradients.py
angler/linalg.py
angler/nonlinear_solvers.py
angler/nonlinearity.py
angler/objective.py
angler/optimization.py
angler/plot.py
angler/pml.py
angler/simulation.py
angler/structures.py
angler/utils.py
angler.egg-info/PKG-INFO
angler.egg-info/SOURCES.txt
angler.egg-info/dependency_links.txt
angler.egg-info/requires.txt
angler.egg-info/top_level.txt
angler/source/__init__.py
angler/source/mode.py
img/Tport.gif
img/favicon.png
img/fields.png