Metadata-Version: 2.1
Name: angler
Version: 0.0.15
Summary: Adjoint Nonlinear Gradients
Home-page: https://github.com/fancompute/angler
Author: Tyler Hughes, Momchil Minkov, Ian Williamson
Author-email: tylerwhughes91@gmail.com
License: UNKNOWN
Platform: UNKNOWN
Classifier: Programming Language :: Python :: 3
Classifier: License :: OSI Approved :: MIT License
Classifier: Operating System :: OS Independent
